next_cvat/__init__.py
next_cvat/__main__.py
next_cvat/access_token.py
next_cvat/annotations.py
next_cvat/app/__init__.py
next_cvat/app/app.py
next_cvat/app/create_token.py
next_cvat/app/download.py
next_cvat/client/__init__.py
next_cvat/client/client.py
next_cvat/client/frame.py
next_cvat/client/job.py
next_cvat/client/job_annotations.py
next_cvat/client/project.py
next_cvat/client/task.py
next_cvat/settings.py
next_cvat/types/__init__.py
next_cvat/types/attribute.py
next_cvat/types/box.py
next_cvat/types/ellipse.py
next_cvat/types/image_annotation.py
next_cvat/types/job_status.py
next_cvat/types/label.py
next_cvat/types/label_attribute.py
next_cvat/types/mask.py
next_cvat/types/polygon.py
next_cvat/types/polyline.py
next_cvat/types/project.py
next_cvat/types/tag.py
next_cvat/types/task.py
next_cvat-0.1.26.dist-info/METADATA
next_cvat-0.1.26.dist-info/WHEEL
next_cvat-0.1.26.dist-info/entry_points.txt
next_cvat-0.1.26.dist-info/RECORD
