Metadata-Version: 2.4
Name: next-cvat
Version: 0.1.26
Summary: Minimalistic python SDK for CVAT
Author: nextml
Requires-Python: >=3.9,<4.0
Classifier: Programming Language :: Python :: 3
Classifier: Programming Language :: Python :: 3.9
Classifier: Programming Language :: Python :: 3.10
Classifier: Programming Language :: Python :: 3.11
Classifier: Programming Language :: Python :: 3.12
Classifier: Programming Language :: Python :: 3.13
Classifier: Programming Language :: Python :: 3.14
Requires-Dist: Pillow
Requires-Dist: cvat-sdk (>=2.43.0,<3.0.0)
Requires-Dist: eval-type-backport ; python_version < "3.10"
Requires-Dist: numpy (>=1.19.2,<2.0.0)
Requires-Dist: pydantic (>=2.0.0,<3.0.0)
Requires-Dist: pydantic-settings (>=2.6.1,<3.0.0)
Requires-Dist: typer
